{"original_fname": "datasets\\ArkosTracker3\\ArkosTracker2\\Totta - Mellow.ym", "compressed_fname": "datasets\\ArkosTracker3\\ArkosTracker2\\Totta - Mellow.fap", "stdout": "\r\nFile header:\r\n  - Nb of frames:    13312\r\n  - Loop Frame:      2048\r\n  - Interleaved:     Yes\r\n\r\nSong Information:\r\n  - Song name: Mellow - Main\r\n  - Author:    Totta\r\n  - Comment:   tottalmedia@gmail.com\r\n\r\nCrunching:\r\n  - Crunch register  0  : 13312 -> 1452\r\n  - Crunch register  2  : 13312 -> 2254\r\n  - Crunch register 1+3 : 13312 -> 890\r\n  - Crunch register  4  : 13312 -> 1730\r\n  - Crunch register 5+13: 13312 -> 149\r\n  - Crunch register  6  : 13312 -> 125\r\n  - Crunch register  7  : 13312 -> 283\r\n  - Crunch register  8  : 13312 -> 464\r\n  - Crunch register  9  : 13312 -> 1331\r\n  - Crunch register 10  : 13312 -> 1652\r\n  - Crunch register 11  : 13312 -> 124\r\n  - Crunch register 12  : Skipped (register is constant)\r\n\r\nSummary:\r\n  - Max registers to program: 11\r\n  - Constant Register 12: YES\r\n  - File size: 10527 (0x291F)\r\n  - Play time: 596 NOPS\r\n  - Decrunch buffer size: 2882 (#B42)\r\n", "stderr": "", "buffer_size": 2882, "data_size": 10527, "play_time": 596, "program_size": 14530}