{"original_fname": "datasets\\ArkosTracker3\\ArkosTracker3\\Doclands - Pong Cracktro (YM).ym", "compressed_fname": "datasets\\ArkosTracker3\\ArkosTracker3\\Doclands - Pong Cracktro (YM).ayt", "stdout": "Opening \"datasets\\\\ArkosTracker3\\\\ArkosTracker3\\\\Doclands - Pong Cracktro (YM).ym\"\r\n----- YM6 HEADER -----\r\nTitle           : In a bind - Overlanders Pong Cracktro 2025 - Main\r\nAuthor          : Cyril Payet\r\nNotes           : Feb 2025. \r\n6 channels version available too !!!!\r\nID              : YM6!\r\nMaster Clock    : 2000000 Hz (ATARI)\r\nFrequency       : 50 Hz\r\nFrame Counter   : 10560\r\nLoop Frame      : 0\r\nAttributs       : $00000001\r\nDigidrums       : 0\r\nInterlaced      : Yes\r\n--------------------------\r\nPeriod Coef = 0.5\r\nNoise Coef = 0.5\r\nEnvelop Coef = 0.5\r\nApplying tone period scaling: x0.5\r\nApplying noise scaling: x0.5\r\nApplying envelope scaling: x0.5\r\nReg13 is constant, but in AYT format V1, it cannot considered as fixed\r\nChanging End of raw registers, repacing with final sequence values\r\nNew Best Pattern size found: 64 (Total Size: 27979 bytes)\r\nNew Best Pattern size found: 48 (Total Size: 20675 bytes)\r\nNew Best Pattern size found: 32 (Total Size: 20230 bytes)\r\nNew Best Pattern size found: 24 (Total Size: 18792 bytes)\r\n\r\nInterlacing 12 sequence buffers Active Regs: 12 Flags=0x2ffd\r\n Pattern Length: 24\r\n Init Sequence: 1=0 12=0 \r\n Loop to sequence : 0\r\n Patterns size : 8208 bytes\r\n Sequences size : 10584 bytes\r\n Total size (sequences + patterns) : 18792 bytes\r\n Total File size: 18811\r\nAYT file \"Doclands - Pong Cracktro (YM).ayt\" saved.\r\n", "stderr": "", "buffer_size": 0, "data_size": 18811, "play_time": -1, "data-size": 18811, "program_size": 19285}